httplink/__init__.py
httplink-0.1.0.dist-info/LICENSE
httplink-0.1.0.dist-info/METADATA
httplink-0.1.0.dist-info/WHEEL
httplink-0.1.0.dist-info/top_level.txt
httplink-0.1.0.dist-info/zip-safe
httplink-0.1.0.dist-info/RECORD
