Metadata-Version: 2.1
Name: httplink
Version: 0.1.0
Summary: Library for parsing RFC 8288 "Link" HTTP headers
Home-page: https://github.com/joernheissler/httplink
Author: Jörn Heissler
Author-email: NOSPAM-httplink@joern.heissler.de
License: MIT
Keywords: rfc8288,Web Linking
Platform: UNKNOWN
Classifier: Development Status :: 4 - Beta
Classifier: Intended Audience :: Developers
Classifier: License :: OSI Approved :: MIT License
Classifier: Programming Language :: Python :: 3
Classifier: Programming Language :: Python :: 3.7
Requires-Python: >= 3.6
